test_app.py
whatever_test_tool-0.0.1.dist-info/METADATA
whatever_test_tool-0.0.1.dist-info/WHEEL
whatever_test_tool-0.0.1.dist-info/top_level.txt
whatever_test_tool-0.0.1.dist-info/RECORD
