Metadata-Version: 2.1
Name: whatever_test_tool
Version: 0.0.1
Summary: test tool
Home-page: UNKNOWN
Author: chris_wu
Author-email: wuhan6582@gmail.com
License: UNKNOWN
Platform: UNKNOWN
